LICENSE
README.md
setup.py
./__main__.py
./ht2sbml.py
./htgraph.py
./mash.py
./CppCode/Makefile
./CppCode/compile.bat
./CppCode/hillTau.py
./CppCode/hillTauSchema.json
./CppCode/ht.cpp
./CppCode/htHeader.h
./CppCode/htbind.cpp
./Examples/HT_MODELS/JsontoGraph.py
./Examples/HT_MODELS/aut6.json
./Examples/HT_MODELS/bcm.json
./Examples/HT_MODELS/bcm_bistable.json
./Examples/HT_MODELS/bistable.json
./Examples/HT_MODELS/conv.json
./Examples/HT_MODELS/conv2ndOrder.json
./Examples/HT_MODELS/eqn.json
./Examples/HT_MODELS/eqn_with_constants.json
./Examples/HT_MODELS/exc.json
./Examples/HT_MODELS/exc2ndOrder.json
./Examples/HT_MODELS/exc_tau_baseline.json
./Examples/HT_MODELS/fb_inhib.json
./Examples/HT_MODELS/ff_inhib.json
./Examples/HT_MODELS/gain.json
./Examples/HT_MODELS/inh.json
./Examples/HT_MODELS/kholodenko.json
./Examples/HT_MODELS/modifier.json
./Examples/HT_MODELS/osc.json
./Examples/HT_MODELS/regressionTest.py
./Examples/HT_MODELS/syn_CaMKIII.json
./Examples/HT_MODELS/syn_S6K.json
./Examples/HT_MODELS/syn_prot1.json
./Examples/HT_MODELS/syn_prot2.json
./Examples/KKIT_MODELS/acc92_fixed.g
./Examples/KKIT_MODELS/autsim_v1_17Jul2020.g
./Examples/KKIT_MODELS/bcm.g
./Examples/KKIT_MODELS/conv.g
./Examples/KKIT_MODELS/conv2ndOrder.g
./Examples/KKIT_MODELS/conv2ndOrder_slow.g
./Examples/KKIT_MODELS/conv_slow.g
./Examples/KKIT_MODELS/exc.g
./Examples/KKIT_MODELS/exc2ndOrder.g
./Examples/KKIT_MODELS/fb_inhib.g
./Examples/KKIT_MODELS/inh.g
./Examples/KKIT_MODELS/kholodenko.g
./Examples/KKIT_MODELS/reverse_bcm.g
./Examples/PaperFigures/bench_native.py
./Examples/PaperFigures/benchmark.py
./Examples/PaperFigures/conv_to_sbml.py
./Examples/PaperFigures/fig1.py
./Examples/PaperFigures/fig1_supp.py
./Examples/PaperFigures/fig2.py
./Examples/PaperFigures/fig3.py
./Examples/PaperFigures/fig3_supp_rev_bcm.py
./Examples/PaperFigures/fig5.py
./Examples/PaperFigures/fig5_supp1.py
./Examples/PaperFigures/fig5_supp2.py
./Examples/PaperFigures/fig5_supp3.py
HillTau.egg-info/PKG-INFO
HillTau.egg-info/SOURCES.txt
HillTau.egg-info/dependency_links.txt
HillTau.egg-info/entry_points.txt
HillTau.egg-info/requires.txt
HillTau.egg-info/top_level.txt