Metadata-Version: 2.1
Name: HillTau
Version: 1.0
Summary: A fast, compact abstraction for model reduction in biochemical signaling networks
Home-page: http://github.com/Bhallalab/HillTau
Author: Upinder S. Bhalla
Author-email: bhalla@ncbs.res.in
Maintainer: HarshaRani
License: GPLv3
Platform: UNKNOWN
License-File: LICENSE
